{
  "id": "ac-export-trend-rezultatyvnosti-po-kpi",
  "type": "measure",
  "name": "AC.Export.Тренд Результативності по KPI (%)",
  "homeTable": "_Measures",
  "displayFolder": "Analytical Cases\\Loss_Productivity\\Export",
  "formatString": "",
  "dataType": "",
  "isHidden": false,
  "description": "",
  "dax": "SELECTEDVALUE('fact_Loss_of_Productivity'[Award_Trend])",
  "dependencies": {
    "measures": [],
    "columns": [
      "fact_Loss_of_Productivity[Award_Trend]"
    ],
    "tables": [
      "fact_Loss_of_Productivity"
    ]
  },
  "lineage": {
    "sourceTables": [
      "DM.vw_R27_fact_Loss_of_Productivity"
    ],
    "sourceColumns": [
      "Award_Trend"
    ],
    "powerQuery": "fact_Loss_of_Productivity"
  },
  "business": {
    "definition": "Award_Trend → Тренд Результативності по KPI (%)",
    "purpose": "",
    "requirementRefs": [
      "Кейс-Втрати-Продуктивності-Працівників"
    ]
  },
  "tags": [
    "analytical-cases",
    "export",
    "loss-productivity",
    "pdp"
  ],
  "source": {
    "repo": "PDP",
    "file": "PDP.SemanticModel/definition/tables/_Measures.tmdl",
    "commit": "49026f60ce142a123a0fccf34706eb5469dd2423",
    "extractedAt": "2026-06-15T12:18:32+03:00"
  },
  "manualNotes": ""
}