{
  "id": "ac-znachennia-peredostannii-roku-otsinky-rezultatyvnosti",
  "type": "measure",
  "name": "AC.Значення передостанній  року оцінки результативності",
  "homeTable": "_Measures",
  "displayFolder": "Analytical Cases\\Burnout_Risk\\Main",
  "formatString": "",
  "dataType": "",
  "isHidden": false,
  "description": "",
  "dax": "\"-\"",
  "reportPages": [],
  "dependencies": {
    "measures": [],
    "columns": [],
    "tables": []
  },
  "usedBy": [],
  "lineage": {
    "sourceTables": [],
    "sourceColumns": [],
    "powerQuery": ""
  },
  "business": {
    "name": "",
    "logic": [],
    "requirementRefs": []
  },
  "tags": [
    "analytical-cases",
    "burnout-risk",
    "main",
    "pdp"
  ],
  "source": {
    "repo": "PDP",
    "file": "PDP.SemanticModel/definition/tables/_Measures.tmdl",
    "commit": "6fe45c40f472d1b6afb7c8e683e258b115d5e842",
    "extractedAt": "2026-06-19T16:48:19+03:00"
  },
  "manualNotes": ""
}