{
  "id": "gp-dolia-komandy-z-kvartalnoiu-premiieiu-fakt",
  "type": "measure",
  "name": "GP.Доля команди з квартальною премією, % факт",
  "homeTable": "_Measures",
  "displayFolder": "Group_Profile\\TRS",
  "formatString": "0.00%;-0.00%;0.00%",
  "dataType": "",
  "isHidden": false,
  "description": "",
  "dax": "//************* ROLE FILTERS **************\nVAR _roleIndex = SELECTEDVALUE ( 't_HierarchyTypes'[Index], 1 )   -- 0 = LT, 1 = Admin\nVAR _filter_lt = TREATAS ( VALUES ( 'dim_Admin_LT_OS'[USER_ACCESS_ID] ),dim_Admin_OS[USER_ACCESS_ID] )\n\n/* *********** ADMIN *********** */\nVAR _admin = \nDIVIDE(\n    CALCULATE(\n        DISTINCTCOUNT('fact_TRS'[USER_ACCESS_ID]),\n        'fact_TRS'[PAYMENTS_FACT_UAH] > 0,\n        'fact_TRS'[TRS_CATEGORY] = \"Змінна винагорода\",\n        'fact_TRS'[SUBCATEGORY_OF_ACCRUAL_TYPE] = \"Квартальні премії\",\n        DATESINPERIOD( 'fact_TRS'[PERIOD], EOMONTH( TODAY(), - 1 ), - 12, MONTH )),\n    [GP.Кількість співробітників всього, чол. - Integer])\n\n/* *********** LT *********** */\nVAR _admin_lt =\nDIVIDE(\n    CALCULATE(\n        DISTINCTCOUNT('fact_TRS'[USER_ACCESS_ID]),\n        'fact_TRS'[PAYMENTS_FACT_UAH] > 0,\n        'fact_TRS'[TRS_CATEGORY] = \"Змінна винагорода\",\n        'fact_TRS'[SUBCATEGORY_OF_ACCRUAL_TYPE] = \"Квартальні премії\",\n        DATESINPERIOD( 'fact_TRS'[PERIOD], EOMONTH( TODAY(), - 1 ), - 12, MONTH ),\n        _filter_lt),\n    [GP.Кількість співробітників всього, чол. - Integer])\n\nVAR _res =\n\tSWITCH (\n\t\t_roleIndex,\n\t\t0, _admin_lt,    -- LT\n\t\t1, _admin,       -- Admin\n\t\t_admin\n\t)\nRETURN \nCOALESCE(_res, \"-\")",
  "reportPages": [
    {
      "display": "Group Profile",
      "slug": "group-profile"
    }
  ],
  "dependencies": {
    "measures": [
      "GP.Кількість співробітників всього, чол. - Integer"
    ],
    "columns": [
      "dim_Admin_LT_OS[USER_ACCESS_ID]",
      "dim_Admin_OS[USER_ACCESS_ID]",
      "fact_TRS[PAYMENTS_FACT_UAH]",
      "fact_TRS[PERIOD]",
      "fact_TRS[SUBCATEGORY_OF_ACCRUAL_TYPE]",
      "fact_TRS[TRS_CATEGORY]",
      "fact_TRS[USER_ACCESS_ID]",
      "t_HierarchyTypes[Index]"
    ],
    "tables": [
      "dim_Admin_OS",
      "fact_TRS",
      "t_HierarchyTypes"
    ]
  },
  "usedBy": [],
  "lineage": {
    "sourceTables": [
      "DM.vw_R27_dim_Employee_Access_List",
      "DM.vw_R27_fact_TRS_PDP"
    ],
    "sourceColumns": [
      "Index",
      "PAYMENTS_FACT_UAH",
      "PERIOD",
      "SUBCATEGORY_OF_ACCRUAL_TYPE",
      "TRS_CATEGORY",
      "USER_ACCESS_ID"
    ],
    "powerQuery": "dim_Admin_OS"
  },
  "business": {
    "name": "",
    "logic": [],
    "requirementRefs": []
  },
  "tags": [
    "group-profile",
    "pdp",
    "trs"
  ],
  "source": {
    "repo": "PDP",
    "file": "PDP.SemanticModel/definition/tables/_Measures.tmdl",
    "commit": "49026f60ce142a123a0fccf34706eb5469dd2423",
    "extractedAt": "2026-06-15T12:18:32+03:00"
  },
  "manualNotes": ""
}