{
  "id": "gp-hodyny-fokusnoi-roboty-napriam",
  "type": "measure",
  "name": "GP.Години фокусної роботи, напрям",
  "homeTable": "_Measures",
  "displayFolder": "Group_Profile\\Viva_Insights",
  "formatString": "",
  "dataType": "",
  "isHidden": false,
  "description": "",
  "dax": "\"-\"",
  "reportPages": [],
  "dependencies": {
    "measures": [],
    "columns": [],
    "tables": []
  },
  "usedBy": [],
  "lineage": {
    "sourceTables": [],
    "sourceColumns": [],
    "powerQuery": ""
  },
  "business": {
    "name": "",
    "logic": [],
    "requirementRefs": []
  },
  "tags": [
    "group-profile",
    "pdp",
    "viva-insights"
  ],
  "source": {
    "repo": "PDP",
    "file": "PDP.SemanticModel/definition/tables/_Measures.tmdl",
    "commit": "a424d2059f3e196794146c8cef8009884c9a1c9b",
    "extractedAt": "2026-06-23T15:19:29+03:00"
  },
  "manualNotes": ""
}