{
  "id": "gp-okr-serednia-otsinka-komandy-znachennia",
  "type": "measure",
  "name": "GP.ОКР.Середня оцінка команди.Значення",
  "homeTable": "_Measures",
  "displayFolder": "Group_Profile\\_Main\\ОКР",
  "formatString": "",
  "dataType": "",
  "isHidden": false,
  "description": "",
  "dax": "//************* ROLE FILTERS **************\nVAR _filter_lt = TREATAS(VALUES(dim_Admin_LT_OS[USER_ACCESS_ID]), 'dim_Admin_OS'[USER_ACCESS_ID])\n\nVAR LastYears = [GP.ОКР.Останній рік]\n    // SUMMARIZE(\n    //     'fact_Employee_OKR', \n    //     'fact_Employee_OKR'[USER_ACCESS_ID], \n    //     \"MaxYear\", MAX('fact_Employee_OKR'[PLAN_YEAR])\n    // )\n/* *********** ADMIN *********** */\nVAR _admin = \n    CALCULATE(\n            AVERAGE('fact_Employee_OKR'[CALC_PERFORMANCE_STR_RATE]),\n            'fact_Employee_OKR'[PLAN_YEAR] = LastYears\n            // TREATAS(LastYearsPerPerson, 'fact_Employee_OKR'[USER_ACCESS_ID], 'fact_Employee_OKR'[PLAN_YEAR])\n        )\n\n/* *********** ADMIN LT *********** */\nVAR _admin_lt = \n    CALCULATE(\n            AVERAGE('fact_Employee_OKR'[CALC_PERFORMANCE_STR_RATE]),\n            'fact_Employee_OKR'[PLAN_YEAR] = LastYears,\n            // TREATAS(LastYearsPerPerson, 'fact_Employee_OKR'[USER_ACCESS_ID], 'fact_Employee_OKR'[PLAN_YEAR]),\n            _filter_lt\n        )\n\n/* *********** RESULT *********** */\nVAR _res = \n\tSWITCH(\n\t\tSELECTEDVALUE( t_HierarchyTypes[Index] ),\n\t\t0, _admin_lt,\n\t\t1, _admin\n\t)\n\nRETURN\nROUND(_res, 2)",
  "reportPages": [],
  "dependencies": {
    "measures": [
      "GP.ОКР.Останній рік"
    ],
    "columns": [
      "dim_Admin_OS[USER_ACCESS_ID]",
      "fact_Employee_OKR[CALC_PERFORMANCE_STR_RATE]",
      "fact_Employee_OKR[PLAN_YEAR]",
      "fact_Employee_OKR[USER_ACCESS_ID]",
      "t_HierarchyTypes[Index]"
    ],
    "tables": [
      "dim_Admin_OS",
      "fact_Employee_OKR",
      "t_HierarchyTypes"
    ]
  },
  "usedBy": [
    "GP.ОКР.Середня Оцінка.Formated",
    "GP.ОКР.Середня оцінка команди.Колір",
    "GP.ОКР.Середня оцінка команди.Текстове поле"
  ],
  "lineage": {
    "sourceTables": [
      "DM.R27_fact_OKR_Goals",
      "DM.vw_R27_dim_Employee_Access_List"
    ],
    "sourceColumns": [
      "CALC_PERFORMANCE_STR_RATE",
      "Index",
      "PLAN_YEAR",
      "USER_ACCESS_ID"
    ],
    "powerQuery": "dim_Admin_OS"
  },
  "business": {
    "name": "",
    "logic": [],
    "requirementRefs": []
  },
  "tags": [
    "group-profile",
    "main",
    "okr",
    "pdp"
  ],
  "source": {
    "repo": "PDP",
    "file": "PDP.SemanticModel/definition/tables/_Measures.tmdl",
    "commit": "6fe45c40f472d1b6afb7c8e683e258b115d5e842",
    "extractedAt": "2026-06-19T16:48:19+03:00"
  },
  "manualNotes": ""
}