{
  "id": "pp-minimum-vylky",
  "type": "measure",
  "name": "PP.Мінімум вилки",
  "homeTable": "_Measures",
  "displayFolder": "Personal_Profile\\TRS",
  "formatString": "#,0",
  "dataType": "",
  "isHidden": false,
  "description": "",
  "dax": "MAX(fact_Employee_List[min_salary_range])",
  "reportPages": [],
  "dependencies": {
    "measures": [],
    "columns": [
      "fact_Employee_List[min_salary_range]"
    ],
    "tables": [
      "fact_Employee_List"
    ]
  },
  "usedBy": [
    "PP.SVG.Позиція в окладній вилці"
  ],
  "lineage": {
    "sourceTables": [],
    "sourceColumns": [
      "min_salary_range"
    ],
    "powerQuery": "fact_Employee_List"
  },
  "business": {
    "definition": "Мінімум вилки",
    "purpose": "Це поле має бути доступне у візуалізаціях, побудованих на основі фактової таблиці [dm.vw_R27_fact_Employee_List]  <br>Якщо значення в полі відсутнє, то показати текст \"Дані відсутні\" або знак \"-\"",
    "requirementRefs": [
      "Індивідуальний-профіль-працівника/Сторінка-Винагорода-працівника"
    ]
  },
  "tags": [
    "pdp",
    "personal-profile",
    "trs"
  ],
  "source": {
    "repo": "PDP",
    "file": "PDP.SemanticModel/definition/tables/_Measures.tmdl",
    "commit": "49026f60ce142a123a0fccf34706eb5469dd2423",
    "extractedAt": "2026-06-15T12:18:32+03:00"
  },
  "manualNotes": ""
}