{
  "id": "pp-otsinka-rezultatyvnosti-poperednii-rik",
  "type": "measure",
  "name": "PP.Оцінка результативності попередній рік",
  "homeTable": "_Measures",
  "displayFolder": "Personal_Profile\\Паспорт\\Результативність",
  "formatString": "",
  "dataType": "",
  "isHidden": false,
  "description": "",
  "dax": "SUM('fact_Burnout_Indicators'[PREV_YEAR_PERFORMANCE_DESC_RATE])",
  "reportPages": [],
  "dependencies": {
    "measures": [],
    "columns": [
      "fact_Burnout_Indicators[PREV_YEAR_PERFORMANCE_DESC_RATE]"
    ],
    "tables": [
      "fact_Burnout_Indicators"
    ]
  },
  "usedBy": [
    "PP.SVG.Perfomance_Prev_Year",
    "PP.SVG.Performance.Last2Periods",
    "PP.Оцінка результативності попередній рік (пусто)"
  ],
  "lineage": {
    "sourceTables": [],
    "sourceColumns": [
      "PREV_YEAR_PERFORMANCE_DESC_RATE"
    ],
    "powerQuery": "fact_Burnout_Indicators"
  },
  "business": {
    "name": "",
    "logic": [],
    "requirementRefs": []
  },
  "tags": [
    "pasport",
    "pdp",
    "personal-profile",
    "rezultatyvnist"
  ],
  "source": {
    "repo": "PDP",
    "file": "PDP.SemanticModel/definition/tables/_Measures.tmdl",
    "commit": "a424d2059f3e196794146c8cef8009884c9a1c9b",
    "extractedAt": "2026-06-23T15:19:29+03:00"
  },
  "manualNotes": ""
}