{
  "id": "pp-otsinka-rezultatyvnosti-bazova",
  "type": "measure",
  "name": "PP.Оцінка результативності базова",
  "homeTable": "_Measures",
  "displayFolder": "Personal_Profile\\Паспорт\\Spider",
  "formatString": "",
  "dataType": "",
  "isHidden": false,
  "description": "",
  "dax": "AVERAGE('fact_Employee_Performance'[Official_Rate])",
  "reportPages": [],
  "dependencies": {
    "measures": [],
    "columns": [
      "fact_Employee_Performance[Official_Rate]"
    ],
    "tables": [
      "fact_Employee_Performance"
    ]
  },
  "usedBy": [
    "PP.Ініціативність при виконанні завдань",
    "PP.Автономність при виконанні завдань",
    "PP.Виконання завдань у встановлені терміни",
    "PP.Відповідність кількості виконаних завдань функціоналу",
    "PP.Націленість на отримання результату",
    "PP.Подолання перешкод при вирішенні проблем",
    "PP.Прийняття відповідальності за отриманий результат",
    "PP.Якість результату виконаних завдань"
  ],
  "lineage": {
    "sourceTables": [
      "DM.vw_R27_fact_Employee_Performance_PBI"
    ],
    "sourceColumns": [
      "Official_Rate"
    ],
    "powerQuery": "fact_Employee_Performance"
  },
  "business": {
    "name": "",
    "logic": [],
    "requirementRefs": []
  },
  "tags": [
    "pasport",
    "pdp",
    "personal-profile",
    "spider"
  ],
  "source": {
    "repo": "PDP",
    "file": "PDP.SemanticModel/definition/tables/_Measures.tmdl",
    "commit": "a424d2059f3e196794146c8cef8009884c9a1c9b",
    "extractedAt": "2026-06-23T15:19:29+03:00"
  },
  "manualNotes": ""
}