{
  "id": "pp-pozyka-aktyvna-suma",
  "type": "measure",
  "name": "PP.Позика (активна).Сума",
  "homeTable": "_Measures",
  "displayFolder": "Personal_Profile\\TRS",
  "formatString": "#,0",
  "dataType": "",
  "isHidden": false,
  "description": "",
  "dax": "CALCULATE(\n    LASTNONBLANKVALUE(\n        'dim_Date'[Date],\n        CALCULATE(SUM(fact_Repayment_Credit[LAND_SHARE_CONTRACT_SUM]))\n    ),\n    'fact_Repayment_Credit'[IS_INCOMING] = TRUE(),\n    'fact_Repayment_Credit'[ACTION_END_DATE] >= EDATE(TODAY(), -12)\n)",
  "reportPages": [
    {
      "display": "Personal Profile",
      "slug": "personal-profile",
      "groups": [
        "Винагорода"
      ]
    }
  ],
  "dependencies": {
    "measures": [],
    "columns": [
      "dim_Date[Date]",
      "fact_Repayment_Credit[ACTION_END_DATE]",
      "fact_Repayment_Credit[IS_INCOMING]",
      "fact_Repayment_Credit[LAND_SHARE_CONTRACT_SUM]"
    ],
    "tables": [
      "dim_Date",
      "fact_Repayment_Credit"
    ]
  },
  "usedBy": [],
  "lineage": {
    "sourceTables": [
      "DM.vw_R27_fact_Repayment_Credit_PDP"
    ],
    "sourceColumns": [
      "ACTION_END_DATE",
      "Date",
      "IS_INCOMING",
      "LAND_SHARE_CONTRACT_SUM"
    ],
    "powerQuery": "dim_Date"
  },
  "business": {
    "name": "",
    "logic": [],
    "requirementRefs": []
  },
  "tags": [
    "pdp",
    "personal-profile",
    "trs"
  ],
  "source": {
    "repo": "PDP",
    "file": "PDP.SemanticModel/definition/tables/_Measures.tmdl",
    "commit": "6fe45c40f472d1b6afb7c8e683e258b115d5e842",
    "extractedAt": "2026-06-19T16:48:19+03:00"
  },
  "manualNotes": ""
}